selenium_project/__init__.py
selenium_project/academic_site/__init__.py
selenium_project/academic_site/dbutils.py
selenium_project/academic_site/main.py
selenium_utils/__init__.py
selenium_utils/browser_utils.py
selenium_utils/colors.py
selenium_utils/image_bytes.py
selenium_utils/logo.py
selenium_utils/multiple_chrome_utils.py
selenium_utils/seleniumObject.py
test/__init__.py
test/mytest.py
selenium_chrome_utils-1.0.3.dist-info/METADATA
selenium_chrome_utils-1.0.3.dist-info/WHEEL
selenium_chrome_utils-1.0.3.dist-info/top_level.txt
selenium_chrome_utils-1.0.3.dist-info/RECORD
